{
  "version": 2,
  "items": [
    {
      "name": "Configurations",
      "children": [
        {
          "name": "ConfigurationHelpers.cs",
          "path": "CommonHelpersLibrary\\ConfigurationHelpers.cs"
        },
        {
          "name": "Info.cs",
          "path": "ProjectPropertiesLibrary\\Info.cs"
        },
        {
          "name": "LoggingSettingsValidation.cs",
          "path": "GetSettingFromAppSettings\\Classes\\LoggingSettingsValidation.cs"
        },
        {
          "name": "Program.cs",
          "path": "SectionExistsAppsettingsApp\\Program.cs"
        }
      ]
    },
    {
      "name": "SystemManagement",
      "children": [
        {
          "name": "Program.cs",
          "path": "ConfigurationTest\\Program.cs"
        }
      ]
    },
    {
      "name": "Index.cshtml",
      "path": "BirthDaysApp\\Pages\\Index.cshtml"
    },
    {
      "name": "index.html",
      "path": "HideShowPasswordSample_1\\index.html"
    },
    {
      "name": "WindowHelper.cs",
      "path": "BootstrapConfirmationApp\\Classes\\WindowHelper.cs"
    }
  ]
}